careamics_napari/__init__.py
careamics_napari/_version.py
careamics_napari/base_plugin.py
careamics_napari/care_plugin.py
careamics_napari/n2n_plugin.py
careamics_napari/n2v_plugin.py
careamics_napari/napari.yaml
careamics_napari/sample_data.py
careamics_napari/bmz/__init__.py
careamics_napari/bmz/author_widget.py
careamics_napari/bmz/bmz_export_widget.py
careamics_napari/careamics_utils/__init__.py
careamics_napari/careamics_utils/algorithms.py
careamics_napari/careamics_utils/callbacks.py
careamics_napari/careamics_utils/care_configs.py
careamics_napari/careamics_utils/configs.py
careamics_napari/careamics_utils/free_memory.py
careamics_napari/careamics_utils/n2n_configs.py
careamics_napari/careamics_utils/n2v_configs.py
careamics_napari/resources/GitHub-Mark-Light-32px.png
careamics_napari/resources/TF_White_Icon.png
careamics_napari/resources/TF_legal_mention.txt
careamics_napari/resources/__init__.py
careamics_napari/resources/gear_16.png
careamics_napari/resources/logo_careamics_v2_128.png
careamics_napari/resources/resources.py
careamics_napari/signals/__init__.py
careamics_napari/signals/prediction_status.py
careamics_napari/signals/saving_signal.py
careamics_napari/signals/saving_status.py
careamics_napari/signals/training_status.py
careamics_napari/utils/__init__.py
careamics_napari/utils/axes_utils.py
careamics_napari/utils/gpu_utils.py
careamics_napari/utils/workers.py
careamics_napari/widgets/__init__.py
careamics_napari/widgets/advanced_config.py
careamics_napari/widgets/axes_widget.py
careamics_napari/widgets/banner_widget.py
careamics_napari/widgets/care_config_window.py
careamics_napari/widgets/folder_widget.py
careamics_napari/widgets/gpu_widget.py
careamics_napari/widgets/magicgui_widgets.py
careamics_napari/widgets/n2n_config_window.py
careamics_napari/widgets/n2v_config_window.py
careamics_napari/widgets/predict_data_widget.py
careamics_napari/widgets/prediction_widget.py
careamics_napari/widgets/qt_widgets.py
careamics_napari-0.0.15.dist-info/licenses/LICENSE
careamics_napari-0.0.15.dist-info/METADATA
careamics_napari-0.0.15.dist-info/WHEEL
careamics_napari-0.0.15.dist-info/entry_points.txt
careamics_napari-0.0.15.dist-info/top_level.txt
careamics_napari-0.0.15.dist-info/RECORD
