Metadata-Version: 2.4
Name: careamics-napari
Version: 0.0.15
Summary: napari plugin providing an interface to CAREamics.
Author-email: Joran Deschamps <joran.deschamps@fht.org>
License: BSD-3-Clause
Project-URL: Bug Tracker, https://github.com/CAREamics/careamics-napari/issues
Project-URL: homepage, https://careamics.github.io/
Project-URL: repository, https://github.com/CAREamics/careamics-napari
Classifier: Development Status :: 3 - Alpha
Classifier: Programming Language :: Python :: 3
Classifier: Programming Language :: Python :: 3.9
Classifier: Programming Language :: Python :: 3.10
Classifier: Programming Language :: Python :: 3.11
Classifier: Programming Language :: Python :: 3.12
Classifier: License :: OSI Approved :: BSD License
Classifier: Typing :: Typed
Requires-Python: >=3.9
License-File: LICENSE
Requires-Dist: qtpy
Requires-Dist: psygnal
Requires-Dist: pyqtgraph
Requires-Dist: napari[all]
Requires-Dist: careamics[tensorboard]
Requires-Dist: careamics-portfolio
Requires-Dist: numcodecs<0.16
Provides-Extra: dev
Requires-Dist: pytest; extra == "dev"
Requires-Dist: pytest-cov; extra == "dev"
Requires-Dist: pytest-qt; extra == "dev"
Requires-Dist: pyqt5; extra == "dev"
Dynamic: license-file
